Workbook

Sheet Dashboard.xlsx - Data
A3: Progress | B3: YTD | C3: Yearly Goal | D3: Progress (%)
A4: Total Revenue ($) | B4: 0 | C4: 1000000 | D4: =Table1[[#This Row],[YTD ]]/Table1[[#This Row],[Yearly Goal ]] -> 0 | E4: =Table1[[#This Row],[Yearly Goal ]]-Table1[[#This Row],[YTD ]] -> 1000000
A5: Number of Google Reviews | B5: =SUM(Table2[Number of Google Reviews]) -> 9 | C5: 10 | D5: =Table1[[#This Row],[YTD ]]/Table1[[#This Row],[Yearly Goal ]] -> 0.9 | E5: =Table1[[#This Row],[Yearly Goal ]]-Table1[[#This Row],[YTD ]] -> 1
A6: New Payroll Clients | B6: =SUM(Table2[New Payroll Clients]) -> 5 | C6: 10 | D6: =Table1[[#This Row],[YTD ]]/Table1[[#This Row],[Yearly Goal ]] -> 0.5 | E6: =Table1[[#This Row],[Yearly Goal ]]-Table1[[#This Row],[YTD ]] -> 5
A7: New Investment Assets ($) | B7: 0 | C7: 1000000 | D7: =Table1[[#This Row],[YTD ]]/Table1[[#This Row],[Yearly Goal ]] -> 0 | E7: =Table1[[#This Row],[Yearly Goal ]]-Table1[[#This Row],[YTD ]] -> 1000000
A8: New Business Services Clients | B8: =SUM(Table2[New Business Services Clients]) -> 5 | C8: 10 | D8: =Table1[[#This Row],[YTD ]]/Table1[[#This Row],[Yearly Goal ]] -> 0.5 | E8: =Table1[[#This Row],[Yearly Goal ]]-Table1[[#This Row],[YTD ]] -> 5
A9: 1040 Audit Protection Taken | B9: 0 | C9: 100 | D9: =Table1[[#This Row],[YTD ]]/Table1[[#This Row],[Yearly Goal ]] -> 0 | E9: =Table1[[#This Row],[Yearly Goal ]]-Table1[[#This Row],[YTD ]] -> 100
A10: Business Audit Protection Taken | B10: 0 | C10: 100 | D10: =Table1[[#This Row],[YTD ]]/Table1[[#This Row],[Yearly Goal ]] -> 0 | E10: =Table1[[#This Row],[Yearly Goal ]]-Table1[[#This Row],[YTD ]] -> 100
A12: Month | B12: Number of Google Reviews | C12: New Payroll Clients | D12: New Business Services Clients
A13: January | B13: 1 | C13: =COUNTA('Payroll Clients Names'!A:A) - 1 -> 4 | D13: =COUNTA('Business Services Clients'!$A:$A) - 1 -> 3
A14: February | B14: 2 | C14: =COUNTA('Payroll Clients Names'!B:B)-1 -> 1 | D14: =COUNTA('Business Services Clients'!$B:$B)-1 -> 1
A15: March | B15: 1 | C15: =COUNTA('Payroll Clients Names'!C:C)-1 -> 0 | D15: =COUNTA('Business Services Clients'!$C:$C)-1 -> 0
A16: April | B16: 1 | C16: =COUNTA('Payroll Clients Names'!D:D)-1 -> 0 | D16: =COUNTA('Business Services Clients'!$D:$D)-1 -> 0
A17: May | B17: 1 | C17: =COUNTA('Payroll Clients Names'!E:E)-1 -> 0 | D17: =COUNTA('Business Services Clients'!$E:$E)-1 -> 0
A18: June | B18: 1 | C18: =COUNTA('Payroll Clients Names'!F:F)-1 -> 0 | D18: =COUNTA('Business Services Clients'!$F:$F)-1 -> 1
A19: July | B19: 1 | C19: =COUNTA('Payroll Clients Names'!G:G)-1 -> 0 | D19: =COUNTA('Business Services Clients'!$G:$G)-1 -> 0
A20: August | B20: 1 | C20: =COUNTA('Payroll Clients Names'!$H:$H)-1 -> 0 | D20: =COUNTA('Business Services Clients'!$H:$H)-1 -> 0
A21: September | B21: 0 | C21: =COUNTA('Payroll Clients Names'!$I:$I)-1 -> 0 | D21: =COUNTA('Business Services Clients'!$I:$I)-1 -> 0
A22: October | B22: 0 | C22: =COUNTA('Payroll Clients Names'!$J:$J)-1 -> 0 | D22: =COUNTA('Business Services Clients'!$J:$J)-1 -> 0
A23: November | B23: 0 | C23: =COUNTA('Payroll Clients Names'!$K:$K)-1 -> 0 | D23: =COUNTA('Business Services Clients'!$K:$K)-1 -> 0
A24: December | B24: 0 | C24: =COUNTA('Payroll Clients Names'!$L:$L)-1 -> 0 | D24: =COUNTA('Business Services Clients'!$L:$L)-1 -> 0
A26: Dashboard Contents
A27: No. of Google Reviews
A28: New Payroll Clients
A29: New Business Services Clients

Sheet Payroll Clients Names
A1: January | B1: February | C1: March | D1: April | E1: May | F1: June | G1: July | H1: August | I1: September | J1: October | K1: November | L1: December
A2: John lloyd | B2: Two medal
A3: Sarah g
A4: Bini
A5: bini maloi

Sheet Business Services Clients
A1: January | B1: February | C1: March | D1: April | E1: May | F1: June | G1: July | H1: August | I1: September | J1: October | K1: November | L1: December
A2: Maloi | B2: Olympics | F2: We
A3: Ahoy
A4: Angelica

Sheet Dashboard
S2: New Payroll Clients
S3: May
S4: {=_xlfn.IFS( $S$2="New Payroll Clients", IF( ISBLANK(_xlfn.XLOOKUP($S$3, 'Payroll Clients Names'!$A$1:$L$1, 'Payroll Clients Names'!$A2:$L2, "", 0, 1)), "", _xlfn.XLOOKUP($S$3, 'Payroll Clients Names'!$A$1:$L$1, 'Payroll Clients Names'!$A2:$L2, "error", 0, 1) ), $S$2="New Business Services Clients", IF( ISBLANK(_xlfn.XLOOKUP($S$3, 'Business Services Clients'!$A$1:$L$1, 'Business Services Clients'!$A2:$L2, "", 0, 1)), "", _xlfn.XLOOKUP($S$3, 'Business Services Clients'!$A$1:$L$1, 'Business Services Clients'!$A2:$L2, "error", 0, 1) ) )}
S5: {=_xlfn.IFS( $S$2="New Payroll Clients", IF( ISBLANK(_xlfn.XLOOKUP($S$3, 'Payroll Clients Names'!$A$1:$L$1, 'Payroll Clients Names'!$A3:$L3, "", 0, 1)), "", _xlfn.XLOOKUP($S$3, 'Payroll Clients Names'!$A$1:$L$1, 'Payroll Clients Names'!$A3:$L3, "error", 0, 1) ), $S$2="New Business Services Clients", IF( ISBLANK(_xlfn.XLOOKUP($S$3, 'Business Services Clients'!$A$1:$L$1, 'Business Services Clients'!$A3:$L3, "", 0, 1)), "", _xlfn.XLOOKUP($S$3, 'Business Services Clients'!$A$1:$L$1, 'Business Services Clients'!$A3:$L3, "error", 0, 1) ) )}
S6: {=_xlfn.IFS( $S$2="New Payroll Clients", IF( ISBLANK(_xlfn.XLOOKUP($S$3, 'Payroll Clients Names'!$A$1:$L$1, 'Payroll Clients Names'!$A4:$L4, "", 0, 1)), "", _xlfn.XLOOKUP($S$3, 'Payroll Clients Names'!$A$1:$L$1, 'Payroll Clients Names'!$A4:$L4, "error", 0, 1) ), $S$2="New Business Services Clients", IF( ISBLANK(_xlfn.XLOOKUP($S$3, 'Business Services Clients'!$A$1:$L$1, 'Business Services Clients'!$A4:$L4, "", 0, 1)), "", _xlfn.XLOOKUP($S$3, 'Business Services Clients'!$A$1:$L$1, 'Business Services Clients'!$A4:$L4, "error", 0, 1) ) )}
S7: {=_xlfn.IFS( $S$2="New Payroll Clients", IF( ISBLANK(_xlfn.XLOOKUP($S$3, 'Payroll Clients Names'!$A$1:$L$1, 'Payroll Clients Names'!$A5:$L5, "", 0, 1)), "", _xlfn.XLOOKUP($S$3, 'Payroll Clients Names'!$A$1:$L$1, 'Payroll Clients Names'!$A5:$L5, "error", 0, 1) ), $S$2="New Business Services Clients", IF( ISBLANK(_xlfn.XLOOKUP($S$3, 'Business Services Clients'!$A$1:$L$1, 'Business Services Clients'!$A5:$L5, "", 0, 1)), "", _xlfn.XLOOKUP($S$3, 'Business Services Clients'!$A$1:$L$1, 'Business Services Clients'!$A5:$L5, "error", 0, 1) ) )}
S8: {=_xlfn.IFS( $S$2="New Payroll Clients", IF( ISBLANK(_xlfn.XLOOKUP($S$3, 'Payroll Clients Names'!$A$1:$L$1, 'Payroll Clients Names'!$A6:$L6, "", 0, 1)), "", _xlfn.XLOOKUP($S$3, 'Payroll Clients Names'!$A$1:$L$1, 'Payroll Clients Names'!$A6:$L6, "error", 0, 1) ), $S$2="New Business Services Clients", IF( ISBLANK(_xlfn.XLOOKUP($S$3, 'Business Services Clients'!$A$1:$L$1, 'Business Services Clients'!$A6:$L6, "", 0, 1)), "", _xlfn.XLOOKUP($S$3, 'Business Services Clients'!$A$1:$L$1, 'Business Services Clients'!$A6:$L6, "error", 0, 1) ) )}
S9: {=_xlfn.IFS( $S$2="New Payroll Clients", IF( ISBLANK(_xlfn.XLOOKUP($S$3, 'Payroll Clients Names'!$A$1:$L$1, 'Payroll Clients Names'!$A7:$L7, "", 0, 1)), "", _xlfn.XLOOKUP($S$3, 'Payroll Clients Names'!$A$1:$L$1, 'Payroll Clients Names'!$A7:$L7, "error", 0, 1) ), $S$2="New Business Services Clients", IF( ISBLANK(_xlfn.XLOOKUP($S$3, 'Business Services Clients'!$A$1:$L$1, 'Business Services Clients'!$A7:$L7, "", 0, 1)), "", _xlfn.XLOOKUP($S$3, 'Business Services Clients'!$A$1:$L$1, 'Business Services Clients'!$A7:$L7, "error", 0, 1) ) )}
S10: {=_xlfn.IFS( $S$2="New Payroll Clients", IF( ISBLANK(_xlfn.XLOOKUP($S$3, 'Payroll Clients Names'!$A$1:$L$1, 'Payroll Clients Names'!$A8:$L8, "", 0, 1)), "", _xlfn.XLOOKUP($S$3, 'Payroll Clients Names'!$A$1:$L$1, 'Payroll Clients Names'!$A8:$L8, "error", 0, 1) ), $S$2="New Business Services Clients", IF( ISBLANK(_xlfn.XLOOKUP($S$3, 'Business Services Clients'!$A$1:$L$1, 'Business Services Clients'!$A8:$L8, "", 0, 1)), "", _xlfn.XLOOKUP($S$3, 'Business Services Clients'!$A$1:$L$1, 'Business Services Clients'!$A8:$L8, "error", 0, 1) ) )}
S11: {=_xlfn.IFS( $S$2="New Payroll Clients", IF( ISBLANK(_xlfn.XLOOKUP($S$3, 'Payroll Clients Names'!$A$1:$L$1, 'Payroll Clients Names'!$A9:$L9, "", 0, 1)), "", _xlfn.XLOOKUP($S$3, 'Payroll Clients Names'!$A$1:$L$1, 'Payroll Clients Names'!$A9:$L9, "error", 0, 1) ), $S$2="New Business Services Clients", IF( ISBLANK(_xlfn.XLOOKUP($S$3, 'Business Services Clients'!$A$1:$L$1, 'Business Services Clients'!$A9:$L9, "", 0, 1)), "", _xlfn.XLOOKUP($S$3, 'Business Services Clients'!$A$1:$L$1, 'Business Services Clients'!$A9:$L9, "error", 0, 1) ) )}
S12: {=_xlfn.IFS( $S$2="New Payroll Clients", IF( ISBLANK(_xlfn.XLOOKUP($S$3, 'Payroll Clients Names'!$A$1:$L$1, 'Payroll Clients Names'!$A10:$L10, "", 0, 1)), "", _xlfn.XLOOKUP($S$3, 'Payroll Clients Names'!$A$1:$L$1, 'Payroll Clients Names'!$A10:$L10, "error", 0, 1) ), $S$2="New Business Services Clients", IF( ISBLANK(_xlfn.XLOOKUP($S$3, 'Business Services Clients'!$A$1:$L$1, 'Business Services Clients'!$A10:$L10, "", 0, 1)), "", _xlfn.XLOOKUP($S$3, 'Business Services Clients'!$A$1:$L$1, 'Business Services Clients'!$A10:$L10, "error", 0, 1) ) )}
S13: {=_xlfn.IFS( $S$2="New Payroll Clients", IF( ISBLANK(_xlfn.XLOOKUP($S$3, 'Payroll Clients Names'!$A$1:$L$1, 'Payroll Clients Names'!$A11:$L11, "", 0, 1)), "", _xlfn.XLOOKUP($S$3, 'Payroll Clients Names'!$A$1:$L$1, 'Payroll Clients Names'!$A11:$L11, "error", 0, 1) ), $S$2="New Business Services Clients", IF( ISBLANK(_xlfn.XLOOKUP($S$3, 'Business Services Clients'!$A$1:$L$1, 'Business Services Clients'!$A11:$L11, "", 0, 1)), "", _xlfn.XLOOKUP($S$3, 'Business Services Clients'!$A$1:$L$1, 'Business Services Clients'!$A11:$L11, "error", 0, 1) ) )}
S14: {=_xlfn.IFS( $S$2="New Payroll Clients", IF( ISBLANK(_xlfn.XLOOKUP($S$3, 'Payroll Clients Names'!$A$1:$L$1, 'Payroll Clients Names'!$A12:$L12, "", 0, 1)), "", _xlfn.XLOOKUP($S$3, 'Payroll Clients Names'!$A$1:$L$1, 'Payroll Clients Names'!$A12:$L12, "error", 0, 1) ), $S$2="New Business Services Clients", IF( ISBLANK(_xlfn.XLOOKUP($S$3, 'Business Services Clients'!$A$1:$L$1, 'Business Services Clients'!$A12:$L12, "", 0, 1)), "", _xlfn.XLOOKUP($S$3, 'Business Services Clients'!$A$1:$L$1, 'Business Services Clients'!$A12:$L12, "error", 0, 1) ) )}
S15: {=_xlfn.IFS( $S$2="New Payroll Clients", IF( ISBLANK(_xlfn.XLOOKUP($S$3, 'Payroll Clients Names'!$A$1:$L$1, 'Payroll Clients Names'!$A13:$L13, "", 0, 1)), "", _xlfn.XLOOKUP($S$3, 'Payroll Clients Names'!$A$1:$L$1, 'Payroll Clients Names'!$A13:$L13, "error", 0, 1) ), $S$2="New Business Services Clients", IF( ISBLANK(_xlfn.XLOOKUP($S$3, 'Business Services Clients'!$A$1:$L$1, 'Business Services Clients'!$A13:$L13, "", 0, 1)), "", _xlfn.XLOOKUP($S$3, 'Business Services Clients'!$A$1:$L$1, 'Business Services Clients'!$A13:$L13, "error", 0, 1) ) )}
... S19: {=_xlfn.IFS( $S$2="New Payroll Clients", IF( ISBLANK(_xlfn.XLOOKUP($S$3, 'Payroll Clients Names'!$A$1:$L$1, 'Payroll Clients Names'!$A17:$L17, "", 0, 1)), "", _xlfn.XLOOKUP($S$3, 'Payroll Clients Names'!$A$1:$L$1, 'Payroll Clients Names'!$A17:$L17, "error", 0, 1) ), $S$2="New Business Services Clients", IF( ISBLANK(_xlfn.XLOOKUP($S$3, 'Business Services Clients'!$A$1:$L$1, 'Business Services Clients'!$A17:$L17, "", 0, 1)), "", _xlfn.XLOOKUP($S$3, 'Business Services Clients'!$A$1:$L$1, 'Business Services Clients'!$A17:$L17, "error", 0, 1) ) )}
B20: View Data | D20: Number of Google Reviews | S20: {=_xlfn.IFS( $S$2="New Payroll Clients", IF( ISBLANK(_xlfn.XLOOKUP($S$3, 'Payroll Clients Names'!$A$1:$L$1, 'Payroll Clients Names'!$A18:$L18, "", 0, 1)), "", _xlfn.XLOOKUP($S$3, 'Payroll Clients Names'!$A$1:$L$1, 'Payroll Clients Names'!$A18:$L18, "error", 0, 1) ), $S$2="New Business Services Clients", IF( ISBLANK(_xlfn.XLOOKUP($S$3, 'Business Services Clients'!$A$1:$L$1, 'Business Services Clients'!$A18:$L18, "", 0, 1)), "", _xlfn.XLOOKUP($S$3, 'Business Services Clients'!$A$1:$L$1, 'Business Services Clients'!$A18:$L18, "error", 0, 1) ) )}
B21: Year to Date | D21: Yearly Goal | F21: Progress | S21: {=_xlfn.IFS( $S$2="New Payroll Clients", IF( ISBLANK(_xlfn.XLOOKUP($S$3, 'Payroll Clients Names'!$A$1:$L$1, 'Payroll Clients Names'!$A19:$L19, "", 0, 1)), "", _xlfn.XLOOKUP($S$3, 'Payroll Clients Names'!$A$1:$L$1, 'Payroll Clients Names'!$A19:$L19, "error", 0, 1) ), $S$2="New Business Services Clients", IF( ISBLANK(_xlfn.XLOOKUP($S$3, 'Business Services Clients'!$A$1:$L$1, 'Business Services Clients'!$A19:$L19, "", 0, 1)), "", _xlfn.XLOOKUP($S$3, 'Business Services Clients'!$A$1:$L$1, 'Business Services Clients'!$A19:$L19, "error", 0, 1) ) )}
B22: =_xlfn.XLOOKUP(D20,'Dashboard.xlsx - Data'!A4:A10,'Dashboard.xlsx - Data'!B4:B10,"invalid input",0,1) -> 9 | D22: =_xlfn.XLOOKUP(D20,'Dashboard.xlsx - Data'!A4:A10,'Dashboard.xlsx - Data'!C4:C10,"invalid input",0,1) -> 10 | F22: =_xlfn.XLOOKUP(D20,'Dashboard.xlsx - Data'!A4:A10,'Dashboard.xlsx - Data'!D4:D10,"invalid input",0,1) -> 0.9 | S22: {=_xlfn.IFS( $S$2="New Payroll Clients", IF( ISBLANK(_xlfn.XLOOKUP($S$3, 'Payroll Clients Names'!$A$1:$L$1, 'Payroll Clients Names'!$A20:$L20, "", 0, 1)), "", _xlfn.XLOOKUP($S$3, 'Payroll Clients Names'!$A$1:$L$1, 'Payroll Clients Names'!$A20:$L20, "error", 0, 1) ), $S$2="New Business Services Clients", IF( ISBLANK(_xlfn.XLOOKUP($S$3, 'Business Services Clients'!$A$1:$L$1, 'Business Services Clients'!$A20:$L20, "", 0, 1)), "", _xlfn.XLOOKUP($S$3, 'Business Services Clients'!$A$1:$L$1, 'Business Services Clients'!$A20:$L20, "error", 0, 1) ) )}
S23: {=_xlfn.IFS( $S$2="New Payroll Clients", IF( ISBLANK(_xlfn.XLOOKUP($S$3, 'Payroll Clients Names'!$A$1:$L$1, 'Payroll Clients Names'!$A21:$L21, "", 0, 1)), "", _xlfn.XLOOKUP($S$3, 'Payroll Clients Names'!$A$1:$L$1, 'Payroll Clients Names'!$A21:$L21, "error", 0, 1) ), $S$2="New Business Services Clients", IF( ISBLANK(_xlfn.XLOOKUP($S$3, 'Business Services Clients'!$A$1:$L$1, 'Business Services Clients'!$A21:$L21, "", 0, 1)), "", _xlfn.XLOOKUP($S$3, 'Business Services Clients'!$A$1:$L$1, 'Business Services Clients'!$A21:$L21, "error", 0, 1) ) )}
I24: Harrenn
S25: {=_xlfn.IFS( S2="New Business Services Clients", "Total " & " " & _xlfn.XLOOKUP(Dashboard!S3,'Dashboard.xlsx - Data'!A13:A24,'Dashboard.xlsx - Data'!D13:D24,"error",0,1), S2="New Payroll Clients", "Total " & " " & _xlfn.XLOOKUP(Dashboard!S3,'Dashboard.xlsx - Data'!A13:A24,'Dashboard.xlsx - Data'!C13:C24,"error",0,1), S2="No. of Google Reviews", "Total " & " " & _xlfn.XLOOKUP(Dashboard!S3,'Dashboard.xlsx - Data'!A13:A24,'Dashboard.xlsx - Data'!B13:B24,"error",0,1) )} -> Total 0
